dantArrays/__init__.py
dantArrays/computed.py
dantArrays/core.py
dantArrays/utils.py
dantarrays-0.0.4.dist-info/METADATA
dantarrays-0.0.4.dist-info/WHEEL
dantarrays-0.0.4.dist-info/RECORD
