Metadata-Version: 2.4
Name: dantArrays
Version: 0.0.4
Summary: A thin wrapper over np.ndarray to provide an intuitive interface for attaching pydantic models as metadata to arrays.
Author-email: Jordan Taylor <jtaylor81284@gmail.com>
Keywords: python
Classifier: Intended Audience :: Developers
Classifier: Programming Language :: Python
Classifier: Programming Language :: Python :: 3
Classifier: Programming Language :: Python :: 3.9
Classifier: Programming Language :: Python :: 3.10
Classifier: Programming Language :: Python :: 3.11
Classifier: Programming Language :: Python :: 3.12
Classifier: Programming Language :: Python :: 3.13
Classifier: Topic :: Software Development :: Libraries :: Python Modules
Requires-Python: <4.0,>=3.10
Requires-Dist: numpy>=2.0.0
Requires-Dist: pydantic>=2.10.6
